whatshow_toolbox/MatlabFuncHelper.py
whatshow_toolbox/__init__.py
whatshow_toolbox-1.0.10.dist-info/METADATA
whatshow_toolbox-1.0.10.dist-info/WHEEL
whatshow_toolbox-1.0.10.dist-info/top_level.txt
whatshow_toolbox-1.0.10.dist-info/RECORD
