Metadata-Version: 2.1
Name: whatshow-toolbox
Version: 1.0.10
Requires-Dist: numpy (>=1.20.1)
